kriptomatte/__init__.py
kriptomatte/kripto_color.py
kriptomatte/kripto_datatypes.py
kriptomatte/kripto_decode.py
kriptomatte/kripto_logger.py
kriptomatte/kripto_utils.py
kriptomatte/pymmh3.py
kriptomatte-0.0.14.dist-info/METADATA
kriptomatte-0.0.14.dist-info/WHEEL
kriptomatte-0.0.14.dist-info/entry_points.txt
kriptomatte-0.0.14.dist-info/licenses/LICENSE
kriptomatte-0.0.14.dist-info/RECORD
