Metadata-Version: 2.3
Name: kriptomatte
Version: 0.0.14
Summary: Decode Cryptomattes in EXR file to PNG masks.
Project-URL: Homepage, https://github.com/GrandArth/Kriptomatte-Phase-1
Project-URL: Issues, https://github.com/GrandArth/Kriptomatte-Phase-1/issues
Author-email: GrandArth <risiamuxms@outlook.com>
License-File: LICENSE
Keywords: Cryptomatte,EXR
Classifier: Development Status :: 1 - Planning
Classifier: License :: OSI Approved :: GNU General Public License v3 (GPLv3)
Classifier: Operating System :: OS Independent
Classifier: Programming Language :: Python :: 3
Requires-Python: >=3.5
Requires-Dist: imath
Requires-Dist: numpy
Requires-Dist: openexr
Requires-Dist: pillow
